changlang_package/__init__.py
changlang_package/__main__.py
changlang_package/runtime.py
changlang_package-1.0.4.dist-info/METADATA
changlang_package-1.0.4.dist-info/WHEEL
changlang_package-1.0.4.dist-info/top_level.txt
changlang_package-1.0.4.dist-info/RECORD
