Metadata-Version: 2.1
Name: changlang-package
Version: 1.0.4
Summary: A custom interpreter for ChangLang
Home-page: UNKNOWN
Author: Benjamin
Author-email: jaehwan8195@gmail.com
License: UNKNOWN
Platform: UNKNOWN
